aws_ork/__init__.py
aws_ork/data/aws_ork.conf
aws_ork/data/salt/aws-ork.sls
aws_ork/data/salt/files/aws_ork.conf
aws_ork/data/sys_init/aws_ork
aws_ork/data/systemd/aws_ork.conf
aws_ork/data/systemd/aws_ork.service
aws_ork-0.4.5.dist-info/DESCRIPTION.rst
aws_ork-0.4.5.dist-info/METADATA
aws_ork-0.4.5.dist-info/RECORD
aws_ork-0.4.5.dist-info/WHEEL
aws_ork-0.4.5.dist-info/entry_points.txt
aws_ork-0.4.5.dist-info/metadata.json
aws_ork-0.4.5.dist-info/top_level.txt
