Metadata-Version: 2.0
Name: aws-ork
Version: 0.4.5
Summary: Daemon listening on SQS for messages from an ASG
Home-page: https://github.com/TriNimbus/aws-ork
Author: Stefan Reimer
Author-email: stefan@trinimbus.com
License: UNKNOWN
Platform: UNKNOWN
Classifier: Development Status :: 4 - Beta
Classifier: Environment :: Web Environment
Classifier: Operating System :: POSIX
Classifier: Programming Language :: Python
Classifier: License :: OSI Approved :: MIT License
Requires-Dist: boto3
Requires-Dist: python-daemon
Requires-Dist: salt
